pypft/__init__.py
pypft/__main__.py
pypft/bessel_mat_handler.py
pypft/open_cache_dir.py
pypft/test_data.npy
pypft/tranform.py
pypft/DHT_impls/__init__.py
pypft/DHT_impls/arrayprogramming.py
pypft/DHT_impls/naive.py
pypft/DHT_impls/parallel.py
pypft/bessel_mat_impls/__init__.py
pypft/bessel_mat_impls/naive.py
pypft/bessel_mat_impls/sym_vect.py
pypft/bessel_mat_impls/sym_vect_par.py
pypft/bessel_mat_impls/symmetric.py
pypft/utils/__init__.py
pypft/utils/coordinates.py
pypft/utils/polar.py
pypft/utils/visualization.py
pypft-0.0.4.dist-info/METADATA
pypft-0.0.4.dist-info/WHEEL
pypft-0.0.4.dist-info/RECORD
