Metadata-Version: 2.4
Name: pypft
Version: 0.0.4
Summary: Polar Fourier Transform for Reconstruction of Polar MR images
Project-URL: Homepage, https://github.com/GhDamghani/PyPFT
Project-URL: Issues, https://github.com/GhDamghani/PyPFT/issues
Author-email: Hossein Ghasem Damghani <hghdamghani@gmail.com>
License-Expression: MIT
Keywords: Hankel Transform,MRI,PFT,Polar MRI
Classifier: Operating System :: OS Independent
Classifier: Programming Language :: Python :: 3
Classifier: Programming Language :: Python :: 3.13
Classifier: Topic :: Scientific/Engineering
Classifier: Topic :: Scientific/Engineering :: Image Processing
Classifier: Topic :: Software Development
Requires-Python: >=3.13
Requires-Dist: joblib>=1.5
Requires-Dist: matplotlib>=2.0
Requires-Dist: numpy>=2.1
Requires-Dist: opencv-python>=4.12
Requires-Dist: platformdirs>=4.4
Requires-Dist: scipy>=1.16
